portfolio/__init__.py
portfolio/portfolio/__init__.py
portfolio/portfolio/asset_groups.py
portfolio/portfolio/constraints.py
portfolio/portfolio/results_logging/__init__.py
portfolio/portfolio/results_logging/plotting.py
portfolio/portfolio/results_logging/results_logging.py
portfolio/resources/__init__.py
portfolio/resources/annual_curves.py
portfolio/resources/commodities.py
portfolio/resources/dispatch.py
portfolio/resources/emissions.py
portfolio/resources/generators.py
portfolio/resources/passive_generators.py
portfolio/resources/storage.py
portfolio/resources/technologies.py
portfolio/scenario/__init__.py
portfolio/scenario/scenarios.py
portfolio/statistics/__init__.py
portfolio/statistics/stochastics.py
portfolio/utils/__init__.py
portfolio/utils/data_utils.py
portfolio/utils/geometry.py
portfolio/utils/manipulation_tools.py
portfolio/utils/simulation_loggers.py
portfolio/utils/time_series_utils.py
electricity_portfolio-0.0.70.dist-info/LICENSE
electricity_portfolio-0.0.70.dist-info/METADATA
electricity_portfolio-0.0.70.dist-info/WHEEL
electricity_portfolio-0.0.70.dist-info/top_level.txt
electricity_portfolio-0.0.70.dist-info/RECORD
